{"is_source_file": true, "format": "JavaScript", "description": "This file sets up custom Jest matchers from the '@testing-library/jest-dom' library for use in testing DOM elements in a React project.", "external_files": ["@testing-library/jest-dom"], "external_methods": ["expect().toHaveTextContent"], "published": [], "classes": [], "methods": [], "calls": ["import '@testing-library/jest-dom'"], "search-terms": ["setupTests.js", "jest-dom", "testing-library", "Jest matchers", "DOM testing", "React testing", "setup"], "state": 2, "file_id": 12, "knowledge_revision": 23, "git_revision": "feba86145ddd5a19d64072341a53864ef5953a61", "ctags": [], "hash": "1a77571e1a8cf36018a41bcedf60db75", "format-version": 4, "code-base-name": "todo_frontend", "filename": "todo_frontend/src/setupTests.js", "revision_history": [{"23": "feba86145ddd5a19d64072341a53864ef5953a61"}]}